LICENSE
MANIFEST.in
README.rst
setup.py
testflows.asserts.egg-info/PKG-INFO
testflows.asserts.egg-info/SOURCES.txt
testflows.asserts.egg-info/dependency_links.txt
testflows.asserts.egg-info/not-zip-safe
testflows.asserts.egg-info/requires.txt
testflows.asserts.egg-info/top_level.txt
testflows/asserts/__init__.py
testflows/asserts/asserts.py
testflows/asserts/helpers.py
tests/tests.py